{
  "trail_id": "42",
  "name": "Bishop Pass Trail to Long Lake",
  "slug": "bishop-pass-long-lake-ca",
  "state": "CA",
  "region": "California",
  "lat": "37.1678",
  "lng": "-118.5717",
  "difficulty": "Moderate",
  "length_mi": "5.0",
  "gain_ft": "1000",
  "best_months": "Jun\u2013Sep",
  "trail_type": "Out & back",
  "park_name": "Inyo National Forest",
  "alerts_url": "https://www.fs.usda.gov/inyo",
  "status": "Open",
  "notes": "South Lake Rd opens mid-May; snow above 10800 ft through June; full pass requires snow travel until late June \u2014 Long Lake turnaround is the right call early season",
  "dog_friendly": "Yes",
  "vehicle_req": "Any",
  "score": 100,
  "score_label": "Great day to go",
  "gear_flags": [
    "wind layer recommended"
  ],
  "current": {
    "temp_f": 52,
    "feels_like_f": 45,
    "wind_mph": 10,
    "gusts_mph": 26,
    "rain_pct": 2
  },
  "sunrise": "2026-05-12T05:48",
  "sunset": "2026-05-12T19:53",
  "aqi": {
    "aqi": 49,
    "category": "Good",
    "pollutant": "O3",
    "source": "airnow"
  },
  "fire": {
    "risk_level": "low",
    "nearest_fire_km": 149.7,
    "fire_count_50km": 0
  },
  "river": null,
  "forecast": [
    {
      "date": "2026-05-12",
      "high_f": 57,
      "low_f": 38,
      "rain_pct": 4,
      "uv": 9,
      "sunrise": "2026-05-12T05:48",
      "sunset": "2026-05-12T19:53",
      "predicted_score": 100,
      "score_label": "Great day to go"
    },
    {
      "date": "2026-05-13",
      "high_f": 50,
      "low_f": 39,
      "rain_pct": 2,
      "uv": 9,
      "sunrise": "2026-05-13T05:47",
      "sunset": "2026-05-13T19:54",
      "predicted_score": 100,
      "score_label": "Great day to go"
    },
    {
      "date": "2026-05-14",
      "high_f": 57,
      "low_f": 36,
      "rain_pct": 2,
      "uv": 9,
      "sunrise": "2026-05-14T05:46",
      "sunset": "2026-05-14T19:55",
      "predicted_score": 100,
      "score_label": "Great day to go"
    },
    {
      "date": "2026-05-15",
      "high_f": 57,
      "low_f": 42,
      "rain_pct": 1,
      "uv": 9,
      "sunrise": "2026-05-15T05:45",
      "sunset": "2026-05-15T19:55",
      "predicted_score": 100,
      "score_label": "Great day to go"
    },
    {
      "date": "2026-05-16",
      "high_f": 51,
      "low_f": 34,
      "rain_pct": 1,
      "uv": 9,
      "sunrise": "2026-05-16T05:44",
      "sunset": "2026-05-16T19:56",
      "predicted_score": 100,
      "score_label": "Great day to go"
    }
  ],
  "updated_at": "2026-05-12T22:36:13.669037+00:00"
}