{
  "trail_id": "36",
  "name": "Half Dome",
  "slug": "half-dome-yosemite-ca",
  "state": "CA",
  "region": "California",
  "lat": "37.7459",
  "lng": "-119.5332",
  "difficulty": "Expert",
  "length_mi": "14.2",
  "gain_ft": "4800",
  "best_months": "May\u2013Oct, cables up",
  "trail_type": "Out & back",
  "park_name": "Yosemite NP",
  "alerts_url": "https://www.nps.gov/yose/planyourvisit/conditions.htm",
  "status": "Open",
  "notes": "Cable permit required May\u2013Oct; lottery in spring \u2014 book early",
  "dog_friendly": "No",
  "vehicle_req": "Any",
  "score": 88,
  "score_label": "Great day to go",
  "gear_flags": [],
  "current": {
    "temp_f": 46,
    "feels_like_f": 40,
    "wind_mph": 7,
    "gusts_mph": 7,
    "rain_pct": 0
  },
  "sunrise": "2026-05-07T05:55",
  "sunset": "2026-05-07T19:53",
  "aqi": {
    "aqi": 38,
    "category": "Good",
    "pollutant": "O3",
    "source": "airnow"
  },
  "fire": {
    "risk_level": "low",
    "nearest_fire_km": null,
    "fire_count_50km": 0
  },
  "river": null,
  "forecast": [
    {
      "date": "2026-05-07",
      "high_f": 56,
      "low_f": 42,
      "rain_pct": 3,
      "uv": 8,
      "sunrise": "2026-05-07T05:55",
      "sunset": "2026-05-07T19:53",
      "predicted_score": 100,
      "score_label": "Great day to go"
    },
    {
      "date": "2026-05-08",
      "high_f": 57,
      "low_f": 44,
      "rain_pct": 0,
      "uv": 9,
      "sunrise": "2026-05-08T05:54",
      "sunset": "2026-05-08T19:54",
      "predicted_score": 100,
      "score_label": "Great day to go"
    },
    {
      "date": "2026-05-09",
      "high_f": 62,
      "low_f": 46,
      "rain_pct": 0,
      "uv": 9,
      "sunrise": "2026-05-09T05:53",
      "sunset": "2026-05-09T19:55",
      "predicted_score": 100,
      "score_label": "Great day to go"
    },
    {
      "date": "2026-05-10",
      "high_f": 69,
      "low_f": 48,
      "rain_pct": 0,
      "uv": 9,
      "sunrise": "2026-05-10T05:52",
      "sunset": "2026-05-10T19:56",
      "predicted_score": 100,
      "score_label": "Great day to go"
    },
    {
      "date": "2026-05-11",
      "high_f": 70,
      "low_f": 48,
      "rain_pct": 0,
      "uv": 9,
      "sunrise": "2026-05-11T05:51",
      "sunset": "2026-05-11T19:57",
      "predicted_score": 100,
      "score_label": "Great day to go"
    }
  ],
  "updated_at": "2026-05-08T04:51:35.166741+00:00"
}